docs/Makefile
docs/README.md
docs/requirements-docs.txt
docs/_source/conf.py
docs/_source/cover.rst
docs/_source/index.rst
docs/_source/xpanse.api.asset_management.rst
docs/_source/xpanse.api.attack_surface_rules.rst
docs/_source/xpanse.api.incident_management.rst
docs/_source/xpanse.api.rst
docs/_source/xpanse.api.tags.rst
docs/_source/xpanse.rst
docs/_source/_static/xpanse_banner.png
examples/asset_management/README.md
examples/asset_management/get_services_by_asset.py
examples/asset_management/requirements.txt
examples/incident_management/README.md
examples/incident_management/requirements.txt
examples/incident_management/update_incidents.py
examples/tags/README.md
examples/tags/assign_and_remove_tags.py
examples/tags/requirements.txt
xpanse/__init__.py
xpanse/client.py
xpanse/const.py
xpanse/endpoint.py
xpanse/error.py
xpanse/iterator.py
xpanse/response.py
xpanse/types.py
xpanse/utils.py
xpanse/api/__init__.py
xpanse/api/asset_management/__init__.py
xpanse/api/asset_management/assets_management_base.py
xpanse/api/asset_management/v1/__init__.py
xpanse/api/asset_management/v1/assets.py
xpanse/api/asset_management/v1/owned_ip_ranges.py
xpanse/api/asset_management/v1/services.py
xpanse/api/attack_surface_rules/__init__.py
xpanse/api/attack_surface_rules/v1/__init__.py
xpanse/api/attack_surface_rules/v1/attack_surface_rules.py
xpanse/api/incident_management/__init__.py
xpanse/api/incident_management/v1/__init__.py
xpanse/api/incident_management/v1/alerts.py
xpanse/api/incident_management/v1/incidents.py
xpanse/api/incident_management/v2/__init__.py
xpanse/api/incident_management/v2/alerts.py
xpanse/api/tags/__init__.py
xpanse/api/tags/v1/__init__.py
xpanse/api/tags/v1/tags.py
xpanse-2.1.0.dist-info/LICENSE
xpanse-2.1.0.dist-info/METADATA
xpanse-2.1.0.dist-info/WHEEL
xpanse-2.1.0.dist-info/top_level.txt
xpanse-2.1.0.dist-info/RECORD
