Metadata-Version: 2.1
Name: xpanse
Version: 2.1.0
Summary: Python library is an interface to the Cortex Xpanse API.
Home-page: UNKNOWN
Author: Palo Alto Cortex Xpanse
Author-email: xpanse-integrations@paloaltonetworks.com
License: ISC
Keywords: xpanse iom
Platform: UNKNOWN
Classifier: Development Status :: 5 - Production/Stable
Classifier: Intended Audience :: Developers
Classifier: Topic :: Software Development
Classifier: Topic :: Software Development :: Libraries
Classifier: Topic :: Software Development :: Libraries :: Application Frameworks
Classifier: Programming Language :: Python :: 3
Classifier: Programming Language :: Python :: 3.7
Classifier: Programming Language :: Python :: 3.8
Classifier: Programming Language :: Python :: 3.9
Classifier: Programming Language :: Python :: 3.10
Requires-Python: >=3.7
License-File: LICENSE
Requires-Dist: requests >=2.25.1
Requires-Dist: deprecated >=1.2.0
Requires-Dist: typing-extensions >=4.5.0
